pyexeqjy/__init__.py
pyexeqjy/entry.py
pyexeqjy/test
pyexeqjy-0.1.7.dist-info/entry_points.txt
pyexeqjy-0.1.7.dist-info/WHEEL
pyexeqjy-0.1.7.dist-info/METADATA
pyexeqjy-0.1.7.dist-info/RECORD
